cfmr/__init__.py
cfmr/emitter.py
cfmr/mapper.py
cfmr/reducer.py
cfmr-0.0.8.dist-info/DESCRIPTION.rst
cfmr-0.0.8.dist-info/METADATA
cfmr-0.0.8.dist-info/RECORD
cfmr-0.0.8.dist-info/WHEEL
cfmr-0.0.8.dist-info/metadata.json
cfmr-0.0.8.dist-info/top_level.txt
